coursetemp/__cli__.py
coursetemp/__init__.py
coursetemp/_version.py
coursetemp/conf/about/coursetemp.yaml
coursetemp/py.typed
course_template-0.1.0.dist-info/LICENSE
course_template-0.1.0.dist-info/METADATA
course_template-0.1.0.dist-info/WHEEL
course_template-0.1.0.dist-info/entry_points.txt
course_template-0.1.0.dist-info/RECORD
