Metadata-Version: 2.1
Name: course-template
Version: 0.1.0
Summary: Streamlined course creation template with interactive documentation support
Home-page: https://entelecheia.github.io/course-template
License: CC-BY-4.0
Author: Young Joon Lee
Author-email: entelecheia@hotmail.com
Requires-Python: >=3.9,<3.13
Classifier: License :: Other/Proprietary License
Classifier: Programming Language :: Python :: 3
Classifier: Programming Language :: Python :: 3.9
Classifier: Programming Language :: Python :: 3.10
Classifier: Programming Language :: Python :: 3.11
Classifier: Programming Language :: Python :: 3.12
Requires-Dist: click (>=8.1.3,<9.0.0)
Project-URL: Repository, https://github.com/entelecheia/course-template
